{
	"configurations" : 
	[
		{
			"directories" : 
			[
				{
					"build" : ".",
					"jsonFile" : "directory-.-Debug-d0094a50bb2071803777.json",
					"minimumCMakeVersion" : 
					{
						"string" : "3.27"
					},
					"projectIndex" : 0,
					"source" : ".",
					"targetIndexes" : 
					[
						0
					]
				}
			],
			"name" : "Debug",
			"projects" : 
			[
				{
					"directoryIndexes" : 
					[
						0
					],
					"name" : "cppdiceroller",
					"targetIndexes" : 
					[
						0
					]
				}
			],
			"targets" : 
			[
				{
					"directoryIndex" : 0,
					"id" : "cppdiceroller::@6890427a1f51a3e7e1df",
					"jsonFile" : "target-cppdiceroller-Debug-c20b9f515559b2a73f6b.json",
					"name" : "cppdiceroller",
					"projectIndex" : 0
				}
			]
		}
	],
	"kind" : "codemodel",
	"paths" : 
	{
		"build" : "F:/dev/AssortedDiceRollers/cppdiceroller/cmake-build-debug",
		"source" : "F:/dev/AssortedDiceRollers/cppdiceroller"
	},
	"version" : 
	{
		"major" : 2,
		"minor" : 6
	}
}
